{
	"name": "dataflow1",
	"properties": {
		"type": "MappingDataFlow",
		"typeProperties": {
			"sources": [
				{
					"dataset": {
						"referenceName": "dsblobhospital",
						"type": "DatasetReference"
					},
					"name": "HospitalData"
				}
			],
			"sinks": [
				{
					"dataset": {
						"referenceName": "dsOutput",
						"type": "DatasetReference"
					},
					"name": "DailyICUOthers"
				},
				{
					"dataset": {
						"referenceName": "dsOutput",
						"type": "DatasetReference"
					},
					"name": "DailyHospitalSurveillance"
				},
				{
					"dataset": {
						"referenceName": "dsOutput",
						"type": "DatasetReference"
					},
					"name": "DailyHospitalOthers"
				},
				{
					"dataset": {
						"referenceName": "dsOutput",
						"type": "DatasetReference"
					},
					"name": "DailyICUSurveillance"
				},
				{
					"dataset": {
						"referenceName": "dsOutput",
						"type": "DatasetReference"
					},
					"name": "WeeklyNewOthers"
				},
				{
					"dataset": {
						"referenceName": "dsOutput",
						"type": "DatasetReference"
					},
					"name": "WeeklyNewSurveillance"
				},
				{
					"dataset": {
						"referenceName": "dsOutput",
						"type": "DatasetReference"
					},
					"name": "WeeklyICUSurveillance"
				},
				{
					"dataset": {
						"referenceName": "dsOutput",
						"type": "DatasetReference"
					},
					"name": "WeeklyICUOthers"
				}
			],
			"transformations": [
				{
					"name": "ConditionalSplit1"
				},
				{
					"name": "Select1"
				}
			],
			"script": "source(output(\n\t\tcountry as string,\n\t\tindicator as string,\n\t\tdate as string,\n\t\tyear_week as string,\n\t\tvalue as string,\n\t\tsource as string,\n\t\turl as string\n\t),\n\tallowSchemaDrift: true,\n\tvalidateSchema: false,\n\tignoreNoFilesFound: false) ~> HospitalData\nSelect1 split( and(equals(indicator, \"Daily hospital occupancy\"), equals(source, \"Surveillance\")),\n\tand(equals(indicator, \"Daily hospital occupancy\"),notEquals(source, \"Surveillance\")),\n\tand(equals(indicator, \"Daily ICU occupancy\"), equals(source, \"Surveillance\")),\n\tand(equals(indicator, \"Daily ICU occupancy\"),notEquals(source, \"Surveillance\")),\n\tand(equals(indicator, \"Weekly new hospital admissions per 100k\"), equals(source, \"Surveillance\")),\n\tand(equals(indicator, \"Weekly new hospital admissions per 100k\"),notEquals(source, \"Surveillance\")),\n\tand(equals(indicator, \"Weekly new ICU admissions per 100k\"), equals(source, \"Surveillance\")),\n\tdisjoint: true) ~> ConditionalSplit1@(DailyHospitalSurveillance, DailyHospitalOthers, DailyICUSurveillance, DailyICUOthers, WeeklyNewSurveillance, WeeklyNewOthers, WeeklyICUSurveillance, WeeklyICUOthers)\nHospitalData select(mapColumn(\n\t\tcountry,\n\t\tindicator,\n\t\tdate,\n\t\tyear_week,\n\t\tvalue,\n\t\tsource\n\t),\n\tskipDuplicateMapInputs: true,\n\tskipDuplicateMapOutputs: true) ~> Select1\nConditionalSplit1@DailyICUOthers sink(allowSchemaDrift: true,\n\tvalidateSchema: false,\n\tpartitionFileNames:['DailyICUOthers.csv'],\n\tskipDuplicateMapInputs: true,\n\tskipDuplicateMapOutputs: true,\n\tpartitionBy('hash', 1)) ~> DailyICUOthers\nConditionalSplit1@DailyHospitalSurveillance sink(allowSchemaDrift: true,\n\tvalidateSchema: false,\n\tpartitionFileNames:['DailyHospitalSurveillance'],\n\tskipDuplicateMapInputs: true,\n\tskipDuplicateMapOutputs: true,\n\tpartitionBy('hash', 1)) ~> DailyHospitalSurveillance\nConditionalSplit1@DailyHospitalOthers sink(allowSchemaDrift: true,\n\tvalidateSchema: false,\n\tpartitionFileNames:['DailyHospitalOthers.csv'],\n\tskipDuplicateMapInputs: true,\n\tskipDuplicateMapOutputs: true,\n\tpartitionBy('hash', 1)) ~> DailyHospitalOthers\nConditionalSplit1@DailyICUSurveillance sink(allowSchemaDrift: true,\n\tvalidateSchema: false,\n\tpartitionFileNames:['DailyICUSurveillance.csv'],\n\tskipDuplicateMapInputs: true,\n\tskipDuplicateMapOutputs: true,\n\tpartitionBy('hash', 1)) ~> DailyICUSurveillance\nConditionalSplit1@WeeklyNewOthers sink(allowSchemaDrift: true,\n\tvalidateSchema: false,\n\tpartitionFileNames:['WeeklyNewOthers.csv'],\n\tskipDuplicateMapInputs: true,\n\tskipDuplicateMapOutputs: true,\n\tpartitionBy('hash', 1)) ~> WeeklyNewOthers\nConditionalSplit1@WeeklyNewSurveillance sink(allowSchemaDrift: true,\n\tvalidateSchema: false,\n\tpartitionFileNames:['WeeklyNewSurveillance.csv'],\n\tskipDuplicateMapInputs: true,\n\tskipDuplicateMapOutputs: true,\n\tpartitionBy('hash', 1)) ~> WeeklyNewSurveillance\nConditionalSplit1@WeeklyICUSurveillance sink(allowSchemaDrift: true,\n\tvalidateSchema: false,\n\tpartitionFileNames:['WeeklyICUSurveillance.csv'],\n\tskipDuplicateMapInputs: true,\n\tskipDuplicateMapOutputs: true,\n\tpartitionBy('hash', 1)) ~> WeeklyICUSurveillance\nConditionalSplit1@WeeklyICUOthers sink(allowSchemaDrift: true,\n\tvalidateSchema: false,\n\tpartitionFileNames:['WeeklyICUOthers.csv'],\n\tskipDuplicateMapInputs: true,\n\tskipDuplicateMapOutputs: true,\n\tpartitionBy('hash', 1)) ~> WeeklyICUOthers"
		}
	}
}